pyomie/__init__.py
pyomie/__main__.py
pyomie/cli.py
pyomie/main.py
pyomie/model.py
pyomie/py.typed
pyomie/util.py
pyomie-1.1.3.dist-info/METADATA
pyomie-1.1.3.dist-info/WHEEL
pyomie-1.1.3.dist-info/entry_points.txt
pyomie-1.1.3.dist-info/licenses/LICENSE
pyomie-1.1.3.dist-info/RECORD
