Metadata-Version: 2.4
Name: pyomie
Version: 1.1.3
Summary: A client for OMIE - Spain and Portugal electricity market data
License: Apache-2.0
License-File: LICENSE
Keywords: omie,electricity,spain,portugal,MIBEL
Author: Luis Miranda
Author-email: soft.road8065@fastmail.com
Requires-Python: >=3.11,<4.0
Classifier: Development Status :: 4 - Beta
Classifier: Intended Audience :: Developers
Classifier: License :: OSI Approved :: Apache Software License
Classifier: Natural Language :: English
Classifier: Operating System :: OS Independent
Classifier: Programming Language :: Python :: 3
Classifier: Programming Language :: Python :: 3.11
Classifier: Programming Language :: Python :: 3.12
Classifier: Programming Language :: Python :: 3.13
Classifier: Programming Language :: Python :: 3.14
Classifier: Topic :: Software Development :: Libraries
Requires-Dist: aiohttp (>=3.9.1,<4.0.0)
Requires-Dist: click (<8.2.0)
Requires-Dist: rich (>=10)
Requires-Dist: typer[all] (>=0.12,<0.13)
Project-URL: Bug Tracker, https://github.com/luuuis/pyomie/issues
Project-URL: Changelog, https://github.com/luuuis/pyomie/blob/main/CHANGELOG.md
Project-URL: Documentation, https://pyomie.readthedocs.io
Project-URL: Repository, https://github.com/luuuis/pyomie
